rnaindel/__init__.py
rnaindel/rnaindel.py
rnaindel/version.py
rnaindel/analysis/__init__.py
rnaindel/analysis/alignment_feature_calculator.py
rnaindel/analysis/analyzer.py
rnaindel/analysis/callset_formatter.py
rnaindel/analysis/classifier.py
rnaindel/analysis/coding_indel.py
rnaindel/analysis/cross_checker.py
rnaindel/analysis/database_feature_calculator.py
rnaindel/analysis/outlier.py
rnaindel/analysis/postprocessor.py
rnaindel/analysis/preprocessor.py
rnaindel/analysis/sequence_properties.py
rnaindel/analysis/timeout.py
rnaindel/analysis/transcript_feature_calculator.py
rnaindel/analysis/utils.py
rnaindel/analysis/vcf_writer.py
rnaindel/defaultcaller/__init__.py
rnaindel/defaultcaller/bambino-1.0.jar
rnaindel/defaultcaller/defaultcaller.py
rnaindel/defaultcaller/mysql-connector-java-5.1.10.jar
rnaindel/defaultcaller/picard.jar
rnaindel/defaultcaller/softclip_realigner.py
rnaindel/defaultcaller/third_party.jar
rnaindel/occurrence/__init__.py
rnaindel/occurrence/counter.py
rnaindel/training/__init__.py
rnaindel/training/downsampler.py
rnaindel/training/feature_selector.py
rnaindel/training/homopolyer_trainer.py
rnaindel/training/model_selection.py
rnaindel/training/model_updater.py
rnaindel/training/parameter_tuner.py
rnaindel/training/result_reporter.py
rnaindel/training/setupper.py
rnaindel/training/trainer.py
rnaindel-3.3.7.dist-info/licenses/LICENSE
rnaindel-3.3.7.dist-info/METADATA
rnaindel-3.3.7.dist-info/WHEEL
rnaindel-3.3.7.dist-info/entry_points.txt
rnaindel-3.3.7.dist-info/top_level.txt
rnaindel-3.3.7.dist-info/RECORD
