Metadata-Version: 2.4
Name: rnaindel
Version: 3.3.7
Summary: Somatic indel discovery tool for tumor RNA-Seq data
Home-page: https://github.com/stjude/RNAIndel
Author: Kohei Hagiwara
Author-email: kohei.hagiwara@stjude.org
License: Apache License 2.0
Requires-Python: >=3.8
License-File: LICENSE
Requires-Dist: ssw-py>=1.0.1
Requires-Dist: pandas>=0.23.0
Requires-Dist: scikit-learn>=0.22.0
Requires-Dist: indelpost>=0.0.4
Dynamic: author
Dynamic: author-email
Dynamic: home-page
Dynamic: license
Dynamic: license-file
Dynamic: requires-dist
Dynamic: requires-python
Dynamic: summary
